{
  "base": "#100d12",
  "mantle": "#1d1a20",
  "crust": "#151218",
  "text": "#e7e0e8",
  "subtext0": "#ccc4cf",
  "subtext1": "#958e99",
  "surface0": "#211e24",
  "surface1": "#2c292f",
  "surface2": "#373339",
  "overlay0": "#e7e0e8",
  "overlay1": "#e7e0e8",
  "overlay2": "#e7e0e8",
  "blue": "#d8bafb",
  "sapphire": "#533b72",
  "peach": "#f2b7c1",
  "green": "#cfc1da",
  "red": "#ffb4ab",
  "mauve": "#d8bafb",
  "pink": "#653b43",
  "yellow": "#4c4357",
  "maroon": "#93000a",
  "teal": "#cfc1da"
}
